boaw.py
boaw-1.0.0.dist-info/LICENSE
boaw-1.0.0.dist-info/METADATA
boaw-1.0.0.dist-info/WHEEL
boaw-1.0.0.dist-info/top_level.txt
boaw-1.0.0.dist-info/RECORD
