Metadata-Version: 2.1
Name: boaw
Version: 1.0.0
Summary: boaw is a library used to keep us stay in online always at work
Author: Muttineni Sai Rohith
Classifier: Programming Language :: Python :: 3
Classifier: License :: OSI Approved :: MIT License
Classifier: Operating System :: OS Independent
Requires-Python: >=3.6
License-File: LICENSE
Requires-Dist: pyautogui
